geo/__init__.py
geo/locator.py
vrv_mygmap-1.0.7.dist-info/LICENSE.txt
vrv_mygmap-1.0.7.dist-info/METADATA
vrv_mygmap-1.0.7.dist-info/WHEEL
vrv_mygmap-1.0.7.dist-info/top_level.txt
vrv_mygmap-1.0.7.dist-info/RECORD
