Metadata-Version: 2.1
Name: vrv-mygmap
Version: 1.0.7
Summary: A small wrapper around google maps api
Home-page: https://github.com/nikhilkumarsingh/mygmap
Author: zoneh
Author-email: oldmonk.h@gmail.com
License: MIT
Keywords: maps location address
Platform: UNKNOWN
Classifier: Development Status :: 4 - Beta
Classifier: Intended Audience :: Developers
Classifier: Topic :: Internet
Classifier: License :: OSI Approved :: MIT License
Classifier: Programming Language :: Python
Classifier: Programming Language :: Python :: 2
Classifier: Programming Language :: Python :: 2.6
Classifier: Programming Language :: Python :: 2.7
Classifier: Programming Language :: Python :: 3
Classifier: Programming Language :: Python :: 3.3
Classifier: Programming Language :: Python :: 3.4
Classifier: Programming Language :: Python :: 3.5
License-File: LICENSE.txt
Requires-Dist: requests
